localdb/__init__.py
localdb.json-1.0.dist-info/LICENSE
localdb.json-1.0.dist-info/METADATA
localdb.json-1.0.dist-info/WHEEL
localdb.json-1.0.dist-info/top_level.txt
localdb.json-1.0.dist-info/RECORD
