Metadata-Version: 2.1
Name: localdb.json
Version: 1.0
Summary: A helper script for easily handling of JSON file as database in local storage.
Home-page: https://github.com/buddhhu/localdb.json
Author: Amit Sharma
Author-email: amitsharma123234@gmail.com
License: GNU AFFERO GENERAL PUBLIC LICENSE (v3)
Platform: UNKNOWN
Classifier: Programming Language :: Python :: 3
Classifier: License :: OSI Approved :: GNU General Public License v3 (GPLv3)
Classifier: Operating System :: OS Independent
License-File: LICENSE
